plover_listening_lookup/config_ui.py
plover_listening_lookup/listening_lookup_config.py
plover_listening_lookup/listening_lookup_macros.py
plover_listening_lookup/listening_lookup_suggestions.py
plover_listening_lookup/listening_lookup_ui.py
plover_listening_lookup/resources_rc.py
plover_listening_lookup-1.0.2.dist-info/LICENSE.txt
plover_listening_lookup-1.0.2.dist-info/METADATA
plover_listening_lookup-1.0.2.dist-info/WHEEL
plover_listening_lookup-1.0.2.dist-info/entry_points.txt
plover_listening_lookup-1.0.2.dist-info/top_level.txt
plover_listening_lookup-1.0.2.dist-info/zip-safe
plover_listening_lookup-1.0.2.dist-info/RECORD
