Metadata-Version: 2.1
Name: plover-listening-lookup
Version: 1.0.2
Summary: Automatic Word Lookup GUI Plugin for Plover
Home-page: https://github.com/Erhannis/plover_listening_lookup
Author: Erhannis
Author-email: eyeillus@gmail.com
License: MIT License (MIT)
Keywords: plover plover_plugin
Classifier: Development Status :: 4 - Beta
Classifier: Environment :: Plugins
Classifier: Intended Audience :: End Users/Desktop
Classifier: License :: OSI Approved :: MIT License
Classifier: Operating System :: OS Independent
Classifier: Programming Language :: Python :: 3
Classifier: Programming Language :: Python :: 3.6
License-File: LICENSE.txt
Requires-Dist: plover>=4.0.0.dev10
